[
  {
    "id": 1,
    "name": "The Legend of Zelda",
    "genre": "Azione",
    "img": "https://picsum.photos/id/111/200/300"
  },
  {
    "id": 2,
    "name": "Hogwarts Legacy",
    "genre": "Azione",
    "img": "https://picsum.photos/id/222/200/300"
  },
  {
    "id": 3,
    "name": "Final Fantasy XVI",
    "genre": "JRPG",
    "img": "https://picsum.photos/id/333/200/300"
  },
  {
    "id": 4,
    "name": "God of War Ragnarök",
    "genre": "Azione",
    "img": "https://picsum.photos/id/444/200/300"
  },
  {
    "id": 5,
    "name": "Minecraft",
    "genre": "Sandbox",
    "img": "https://picsum.photos/id/555/200/300"
  }
]